MANIFEST.in
setup.py
cython_zstd.egg-info/PKG-INFO
cython_zstd.egg-info/SOURCES.txt
cython_zstd.egg-info/dependency_links.txt
cython_zstd.egg-info/top_level.txt
zstd/__init__.py
zstd/_bindings.c
zstd/_bindings.pyx