Metadata-Version: 1.1
Name: cython-zstd
Version: 0.2
Summary: Zstd bindings for Python
Home-page: https://lab.nexedi.com/nexedi/cython-zstd
Author: Nexedi
Author-email: jm@nexedi.com
License: GPL 2+
Platform: UNKNOWN
Classifier: License :: OSI Approved :: GNU General Public License v2 or later (GPLv2+)
Classifier: Programming Language :: Cython
Classifier: Programming Language :: Python :: 2
Classifier: Programming Language :: Python :: 3
